newio_requests/__about__.py
newio_requests/__init__.py
newio_requests/adapters.py
newio_requests/api.py
newio_requests/connection_pool.py
newio_requests/cuhttp.py
newio_requests/exceptions.py
newio_requests/future.py
newio_requests/http.py
newio_requests/models.py
newio_requests/network.py
newio_requests/resource_pool.py
newio_requests/sessions.py
newio_requests/utils.py
newio_requests-0.6.0.dist-info/DESCRIPTION.rst
newio_requests-0.6.0.dist-info/METADATA
newio_requests-0.6.0.dist-info/RECORD
newio_requests-0.6.0.dist-info/WHEEL
newio_requests-0.6.0.dist-info/metadata.json
newio_requests-0.6.0.dist-info/top_level.txt
