Metadata-Version: 2.0
Name: newio-requests
Version: 0.6.0
Summary: Newio + Requests: Async HTTP for Humans.
Home-page: https://github.com/guyskk/newio-requests
Author: guyskk
Author-email: guyskk@qq.com
License: MIT
Platform: UNKNOWN
Classifier: Intended Audience :: Developers
Classifier: License :: OSI Approved :: MIT License
Classifier: Operating System :: OS Independent
Classifier: Programming Language :: Python :: 3 :: Only
Classifier: Programming Language :: Python :: 3.6
Classifier: Topic :: Software Development :: Libraries :: Python Modules
Requires-Dist: httptools
Requires-Dist: yarl
Requires-Dist: newio (>=0.6.1)
Requires-Dist: requests
Requires-Dist: namedlist
Provides-Extra: dev
Requires-Dist: pre-commit (==1.10.2); extra == 'dev'
Requires-Dist: tox (==2.9.1); extra == 'dev'
Requires-Dist: flake8 (==3.5.0); extra == 'dev'
Requires-Dist: pytest (==3.3.2); extra == 'dev'
Requires-Dist: pytest-cov (==2.5.1); extra == 'dev'
Requires-Dist: codecov (==2.0.13); extra == 'dev'
Requires-Dist: pytest-httpbin (==0.3.0); extra == 'dev'
Requires-Dist: invoke (==0.22.0); extra == 'dev'
Requires-Dist: twine (==1.9.1); extra == 'dev'
Requires-Dist: wheel (==0.30.0); extra == 'dev'
Requires-Dist: bumpversion (==0.5.3); extra == 'dev'
